codearena/__init__.py
codearena/codearena.py
codearena-0.0.5.dist-info/LICENSE
codearena-0.0.5.dist-info/METADATA
codearena-0.0.5.dist-info/WHEEL
codearena-0.0.5.dist-info/top_level.txt
codearena-0.0.5.dist-info/RECORD
