Metadata-Version: 2.1
Name: codearena
Version: 0.0.5
Summary: CodeArena Python SDK
Home-page: https://codellm.club
Author: Mingzhe Du
Author-email: mingzhe@nus.edu.sg
License: MIT
Classifier: Programming Language :: Python :: 3
Classifier: License :: OSI Approved :: GNU General Public License v3 (GPLv3)
Classifier: Operating System :: OS Independent
Requires-Python: >=3
License-File: LICENSE
